{
    "id": 88421468,
    "name": "AKIRA",
    "author": "Denni",
    "creators": [],
    "verifier": "Turtle",
    "verification": "https://www.youtube.com/watch?v=C4gKotsxh3I",
    "percentToQualify": "100",
    "password": "Free To Copy",
    "records": [    
    {
            "user": "Kopre",
            "link": "https://www.youtube.com/watch?v=QP4IyWZG4d0",
            "percent": 100,
            "hz": 360
         },
            {
            "user": "Cryostaz",
            "link": "https://youtu.be/BWanZ2qx1ZU?si=ghYS1QP3VsAD7Seg",
            "percent": 100,
            "hz": 360
         }
    ]
}
