{
    "id": 86018142,
    "name": "Kyouki",
    "author": "Demishio",
    "creators": [],
    "verifier": "Turtle",
    "verification": "https://youtu.be/eFCUtENP0F0?si=zHQZtim2oo6V23be",
    "percentToQualify": "72",
    "password": "Free To Copy",
    "records": [
          {
            "user": "JohnLikesDiamond",
            "link": "https://youtu.be/9ug7JkgXlwE?si=cAwp6w5RK1CRh9IE",
            "percent": 100,
            "hz": 360
         },
        {
            "user": "Duv",
            "link": "https://www.youtube.com/watch?v=-UbdLrk6yBw&ab_channel=Duv",
            "percent": 83,
            "hz": 360
         }
    ]
}
