{
    "id": 85133223,
    "name": "poocubed",
    "author": "Liisp",
    "creators": [],
    "verifier": "JohnLikesDiamond",
    "verification": "https://youtu.be/JpPwflzKW4w?si=33v5yAqxDy1HreJX",
    "percentToQualify": "61",
    "password": "Free To Copy",
    "records": [       
        {
            "user": "Kopre",
            "link": "https://youtu.be/RPn6nQ_OpRw?si=Qfh6Jd6khJx2tBdB",
            "percent": 100,
            "hz": 360
         },
          {
            "user": "Lus",
            "link": "https://www.youtube.com/watch?v=3qa02hy5Cdw",
            "percent": 100,
            "hz": 360
         },
          {
            "user": "Fxrmula",
            "link": "https://youtu.be/3_-BV6bQxVE?si=lJhwP0IPr9FrieBd",
            "percent": 95,
            "hz": 360
         }
    ]
}
